Metadata-Version: 1.0
Name: austysproject
Version: 0.1
Summary: My Project
Home-page: UNKNOWN
Author: Austin
Author-email: austinngo38@gmail.com
License: UNKNOWN
Platform: UNKNOWN
